{
  "video_file": "IMG_3731.MOV",
  "image_path": "C:/Users/sdris/Documents/git/waterpolo-xg/app/reports/frames/8-8-p0021-q4-n13-standard_t0.jpg",
  "image_shape": {
    "h": 2160,
    "w": 3840
  },
  "H": [
    [
      -0.001998111917894499,
      0.029384494078279658,
      -26.71191993538795
    ],
    [
      0.007784523200645635,
      0.011832002296984213,
      -18.812412808677827
    ],
    [
      5.4040068283702935e-05,
      0.0013415649507488412,
      1.0
    ]
  ],
  "points_px": [
    [
      999.0326866861546,
      943.9277172468775
    ],
    [
      1710.2949774116396,
      451.0443794844539
    ],
    [
      3127.717246877491,
      497.98564974754186
    ],
    [
      1602.1259633271325,
      878.6181238373638
    ],
    [
      2712.389051288865,
      1085.771990433165
    ],
    [
      444.92160510231196,
      1347.0103640712198
    ]
  ],
  "points_m": [
    [
      0.0,
      0.0
    ],
    [
      -10.0,
      0.0
    ],
    [
      -10.0,
      6.0
    ],
    [
      -2.0,
      2.0
    ],
    [
      0.0,
      6.0
    ],
    [
      4.0,
      0.0
    ]
  ],
  "notes": "Pixel\u2192meter homography. x_m in [-10..+10], y_m in [0..15].",
  "reference_frame": "C:\\Users\\sdris\\Documents\\git\\waterpolo-xg\\app\\reports\\frames\\8-8-p0021-q4-n13-standard_t0.jpg",
  "meta": {
    "propagated_from": "C:\\Users\\sdris\\Documents\\git\\waterpolo-xg\\app\\reports\\frames\\8-8-p0021-q4-n13-standard_t0.jpg",
    "inliers": 3000,
    "good_matches": 3000
  },
  "homography": {
    "matrix": [
      [
        1.0000000000000122,
        5.865759039309844e-15,
        -1.1938317248423105e-11
      ],
      [
        1.785743908586757e-15,
        1.0000000000000102,
        -5.4846614907358456e-12
      ],
      [
        2.384445639871236e-18,
        3.0415545669990386e-18,
        1.0
      ]
    ]
  }
}